{
  "_class": "group",
  "do_objectID": "BCB47EBA-13FB-4EE7-9010-ABD17F5CCB9F",
  "exportOptions": {
    "_class": "exportOptions",
    "exportFormats": [
    ],
    "includedLayerIds": [
    ],
    "layerOptions": 0,
    "shouldTrim": false
  },
  "frame": {
    "_class": "rect",
    "constrainProportions": false,
    "height": 40,
    "width": 416,
    "x": 304,
    "y": 76
  },
  "hasClickThrough": false,
  "isFlippedHorizontal": false,
  "isFlippedVertical": false,
  "isLocked": false,
  "isVisible": true,
  "layerListExpandedType": 0,
  "layers": [
    {
      "class": "group",
      "id": "DE64391C-1E46-4728-A071-2F262077EA97"
    },
    {
      "class": "group",
      "id": "050A8BFC-002E-4AF3-906E-4C37B5FD3979"
    },
    {
      "class": "shapeGroup",
      "id": "32A62C25-97F5-4601-B07A-0DA00C17DD14"
    },
    {
      "class": "text",
      "id": "47DB35D4-4456-4886-96A1-60F24DE4F727"
    }
  ],
  "name": "BTN GROUP",
  "nameIsFixed": true,
  "resizingConstraint": 63,
  "resizingType": 0,
  "rotation": 0,
  "shouldBreakMaskChain": false,
  "style": {
    "_class": "style",
    "endDecorationType": 0,
    "miterLimit": 10,
    "startDecorationType": 0
  }
}