{
  "_class": "shapePath",
  "booleanOperation": -1,
  "do_objectID": "689CC4B1-C6D9-4F27-A90D-6D9B60860323",
  "edited": true,
  "exportOptions": {
    "_class": "exportOptions",
    "exportFormats": [
    ],
    "includedLayerIds": [
    ],
    "layerOptions": 0,
    "shouldTrim": false
  },
  "frame": {
    "_class": "rect",
    "constrainProportions": false,
    "height": 2.000000000000002,
    "width": 2.095238095238102,
    "x": 1.904761904761898,
    "y": 0
  },
  "isFlippedHorizontal": false,
  "isFlippedVertical": false,
  "isLocked": false,
  "isVisible": true,
  "layerListExpandedType": 0,
  "name": "Shape-path",
  "nameIsFixed": false,
  "path": {
    "_class": "path",
    "isClosed": true,
    "pointRadiusBehaviour": 1,
    "points": [
      {
        "_class": "curvePoint",
        "cornerRadius": 0,
        "curveFrom": "{0.81818181818181579, 0}",
        "curveMode": 1,
        "curveTo": "{0.81818181818181579, 0}",
        "hasCurveFrom": false,
        "hasCurveTo": false,
        "point": "{0.81818181818181579, 0}"
      },
      {
        "_class": "curvePoint",
        "cornerRadius": 0,
        "curveFrom": "{0.49999999999999678, 0.72727272727272674}",
        "curveMode": 1,
        "curveTo": "{0.49999999999999678, 0.72727272727272674}",
        "hasCurveFrom": false,
        "hasCurveTo": false,
        "point": "{0.49999999999999678, 0.72727272727272674}"
      },
      {
        "_class": "curvePoint",
        "cornerRadius": 0,
        "curveFrom": "{0.22727272727272699, 0}",
        "curveMode": 1,
        "curveTo": "{0.22727272727272699, 0}",
        "hasCurveFrom": false,
        "hasCurveTo": false,
        "point": "{0.22727272727272699, 0}"
      },
      {
        "_class": "curvePoint",
        "cornerRadius": 0,
        "curveFrom": "{0, 0}",
        "curveMode": 1,
        "curveTo": "{0, 0}",
        "hasCurveFrom": false,
        "hasCurveTo": false,
        "point": "{0, 0}"
      },
      {
        "_class": "curvePoint",
        "cornerRadius": 0,
        "curveFrom": "{0, 1}",
        "curveMode": 1,
        "curveTo": "{0, 1}",
        "hasCurveFrom": false,
        "hasCurveTo": false,
        "point": "{0, 1}"
      },
      {
        "_class": "curvePoint",
        "cornerRadius": 0,
        "curveFrom": "{0.13636363636363488, 1}",
        "curveMode": 1,
        "curveTo": "{0.13636363636363488, 1}",
        "hasCurveFrom": false,
        "hasCurveTo": false,
        "point": "{0.13636363636363488, 1}"
      },
      {
        "_class": "curvePoint",
        "cornerRadius": 0,
        "curveFrom": "{0.13636363636363488, 0.22727272727272715}",
        "curveMode": 1,
        "curveTo": "{0.13636363636363488, 0.22727272727272715}",
        "hasCurveFrom": false,
        "hasCurveTo": false,
        "point": "{0.13636363636363488, 0.22727272727272715}"
      },
      {
        "_class": "curvePoint",
        "cornerRadius": 0,
        "curveFrom": "{0.45454545454545398, 1}",
        "curveMode": 1,
        "curveTo": "{0.45454545454545398, 1}",
        "hasCurveFrom": false,
        "hasCurveTo": false,
        "point": "{0.45454545454545398, 1}"
      },
      {
        "_class": "curvePoint",
        "cornerRadius": 0,
        "curveFrom": "{0.54545454545454608, 1}",
        "curveMode": 1,
        "curveTo": "{0.54545454545454608, 1}",
        "hasCurveFrom": false,
        "hasCurveTo": false,
        "point": "{0.54545454545454608, 1}"
      },
      {
        "_class": "curvePoint",
        "cornerRadius": 0,
        "curveFrom": "{0.86363636363635865, 0.22727272727272715}",
        "curveMode": 1,
        "curveTo": "{0.86363636363635865, 0.22727272727272715}",
        "hasCurveFrom": false,
        "hasCurveTo": false,
        "point": "{0.86363636363635865, 0.22727272727272715}"
      },
      {
        "_class": "curvePoint",
        "cornerRadius": 0,
        "curveFrom": "{0.86363636363635865, 1}",
        "curveMode": 1,
        "curveTo": "{0.86363636363635865, 1}",
        "hasCurveFrom": false,
        "hasCurveTo": false,
        "point": "{0.86363636363635865, 1}"
      },
      {
        "_class": "curvePoint",
        "cornerRadius": 0,
        "curveFrom": "{1, 1}",
        "curveMode": 1,
        "curveTo": "{1, 1}",
        "hasCurveFrom": false,
        "hasCurveTo": false,
        "point": "{1, 1}"
      },
      {
        "_class": "curvePoint",
        "cornerRadius": 0,
        "curveFrom": "{1, 0}",
        "curveMode": 1,
        "curveTo": "{1, 0}",
        "hasCurveFrom": false,
        "hasCurveTo": false,
        "point": "{1, 0}"
      }
    ]
  },
  "resizingConstraint": 63,
  "resizingType": 0,
  "rotation": 0,
  "shouldBreakMaskChain": false
}