{
  "_class": "group",
  "do_objectID": "F45EAE1E-0238-4AD6-BAF2-16A7BF29381A",
  "exportOptions": {
    "_class": "exportOptions",
    "exportFormats": [
    ],
    "includedLayerIds": [
    ],
    "layerOptions": 0,
    "shouldTrim": false
  },
  "frame": {
    "_class": "rect",
    "constrainProportions": false,
    "height": 331,
    "width": 324,
    "x": 24,
    "y": 372
  },
  "hasClickThrough": false,
  "isFlippedHorizontal": false,
  "isFlippedVertical": false,
  "isLocked": false,
  "isVisible": false,
  "layerListExpandedType": 0,
  "layers": [
    {
      "class": "shapeGroup",
      "id": "F14B8422-608E-4B4E-ACFF-9BE5DCF4E172"
    },
    {
      "class": "shapeGroup",
      "id": "1AFA303C-6507-4A36-8116-2760CACB9CB9"
    },
    {
      "class": "text",
      "id": "3B8647D4-28C9-408E-9C20-3079EF764BBF"
    },
    {
      "class": "text",
      "id": "EF43C66E-1730-4A4E-B62D-219EC65AFA6C"
    }
  ],
  "name": "Group",
  "nameIsFixed": false,
  "resizingConstraint": 63,
  "resizingType": 0,
  "rotation": 0,
  "shouldBreakMaskChain": false,
  "style": {
    "_class": "style",
    "endDecorationType": 0,
    "miterLimit": 10,
    "startDecorationType": 0
  }
}