{
  "_class": "group",
  "do_objectID": "03CF12FB-4CF3-4529-9892-A6DB7092F8F1",
  "exportOptions": {
    "_class": "exportOptions",
    "exportFormats": [
    ],
    "includedLayerIds": [
    ],
    "layerOptions": 0,
    "shouldTrim": false
  },
  "frame": {
    "_class": "rect",
    "constrainProportions": false,
    "height": 19,
    "width": 406,
    "x": 371,
    "y": 74
  },
  "hasClickThrough": false,
  "isFlippedHorizontal": false,
  "isFlippedVertical": false,
  "isLocked": false,
  "isVisible": true,
  "layerListExpandedType": 0,
  "layers": [
    {
      "class": "text",
      "id": "08280DE5-36B4-40B8-BA6B-87EA34096EDE"
    },
    {
      "class": "text",
      "id": "79C01CB5-ADBC-4391-BEFC-021C27FDBE97"
    }
  ],
  "name": "Key",
  "nameIsFixed": true,
  "resizingConstraint": 63,
  "resizingType": 0,
  "rotation": 0,
  "shouldBreakMaskChain": false,
  "style": {
    "_class": "style",
    "endDecorationType": 0,
    "miterLimit": 10,
    "startDecorationType": 0
  }
}