{
  "_class": "group",
  "do_objectID": "C357FF33-8B94-4FF8-95C7-3644A730605A",
  "exportOptions": {
    "_class": "exportOptions",
    "exportFormats": [
    ],
    "includedLayerIds": [
    ],
    "layerOptions": 0,
    "shouldTrim": false
  },
  "frame": {
    "_class": "rect",
    "constrainProportions": false,
    "height": 40,
    "width": 50,
    "x": 255,
    "y": 0
  },
  "hasClickThrough": false,
  "isFlippedHorizontal": false,
  "isFlippedVertical": false,
  "isLocked": false,
  "isVisible": true,
  "layerListExpandedType": 0,
  "layers": [
    {
      "class": "shapeGroup",
      "id": "956419C9-BD52-4182-A78B-A6A72F228BD2"
    },
    {
      "class": "text",
      "id": "6D572092-005D-4797-9569-8B0D30DCFB30"
    }
  ],
  "name": "5",
  "nameIsFixed": true,
  "resizingConstraint": 63,
  "resizingType": 0,
  "rotation": 0,
  "shouldBreakMaskChain": false,
  "style": {
    "_class": "style",
    "endDecorationType": 0,
    "miterLimit": 10,
    "startDecorationType": 0
  }
}