{
  "_class": "group",
  "do_objectID": "EF44E5AC-E019-49E3-886E-2C20D6972A17",
  "exportOptions": {
    "_class": "exportOptions",
    "exportFormats": [
    ],
    "includedLayerIds": [
    ],
    "layerOptions": 0,
    "shouldTrim": false
  },
  "frame": {
    "_class": "rect",
    "constrainProportions": false,
    "height": 34,
    "width": 144,
    "x": 12,
    "y": 8
  },
  "hasClickThrough": false,
  "isFlippedHorizontal": false,
  "isFlippedVertical": false,
  "isLocked": false,
  "isVisible": true,
  "layerListExpandedType": 0,
  "layers": [
    {
      "class": "group",
      "id": "0ABC1A10-1FCD-402D-A144-D0F3AD8D5763"
    },
    {
      "class": "group",
      "id": "C480CAF4-0146-4068-8597-76020C35519A"
    },
    {
      "class": "group",
      "id": "F498DDEB-95A7-4D11-8572-6B4318E226E9"
    },
    {
      "class": "group",
      "id": "8AF453B0-438C-499D-B131-B489F4E36E2F"
    },
    {
      "class": "shapeGroup",
      "id": "9CDB5958-73B7-442C-A603-5377C4D25BCF"
    },
    {
      "class": "bitmap",
      "id": "846202C5-0379-4713-964E-E684EACF52EF"
    }
  ],
  "name": "People Circles",
  "nameIsFixed": true,
  "resizingConstraint": 63,
  "resizingType": 0,
  "rotation": 0,
  "shouldBreakMaskChain": false,
  "style": {
    "_class": "style",
    "endDecorationType": 0,
    "miterLimit": 10,
    "startDecorationType": 0
  }
}